platform_monitor_client/__init__.py
platform_monitor_client/monitor_thread.py
platformo_client-0.0.1.dist-info/DESCRIPTION.rst
platformo_client-0.0.1.dist-info/METADATA
platformo_client-0.0.1.dist-info/RECORD
platformo_client-0.0.1.dist-info/WHEEL
platformo_client-0.0.1.dist-info/metadata.json
platformo_client-0.0.1.dist-info/top_level.txt
