Metadata-Version: 2.0
Name: platformo-client
Version: 0.0.1
Summary: 收集Flask的请求响应时间并发送至logstash
Home-page: UNKNOWN
Author: zhengz
Author-email: zhengz@miriding.com
License: MIT
Keywords: logstash flask
Platform: UNKNOWN
Requires-Dist: requests
